{
    "appName": "NergalCv",
    "roleName": "pinpointLambdaRole45762b12",
    "cloudformationPolicyName": "cloudformationPolicy45762b12",
    "cloudWatchPolicyName": "cloudWatchPolicy45762b12",
    "pinpointPolicyName": "pinpointPolicy45762b12",
    "authPolicyName": "pinpoint_amplify_45762b12",
    "unauthPolicyName": "pinpoint_amplify_45762b12",
    "authRoleName": {
        "Ref": "AuthRoleName"
    },
    "unauthRoleName": {
        "Ref": "UnauthRoleName"
    },
    "authRoleArn": {
        "Fn::GetAtt": [
            "AuthRole",
            "Arn"
        ]
    }
}